{"user":{"screen_name": "SenatorShaheen"},"id": 917857177519513600}
{"user":{"screen_name": "SenatorShaheen"},"id": 916378713444569088}
{"user":{"screen_name": "SenatorShaheen"},"id": 914855416961609728}
{"user":{"screen_name": "SenatorShaheen"},"id": 914519846498553856}
{"user":{"screen_name": "SenatorShaheen"},"id": 912800426478784513}
{"user":{"screen_name": "SenatorShaheen"},"id": 910965374262407168}
{"user":{"screen_name": "SenatorShaheen"},"id": 910534339296944133}
{"user":{"screen_name": "SenatorShaheen"},"id": 910498124459802625}
{"user":{"screen_name": "SenatorShaheen"},"id": 908329215388471296}
{"user":{"screen_name": "SenatorShaheen"},"id": 908011895868858371}
{"user":{"screen_name": "SenatorShaheen"},"id": 907971995966607360}
{"user":{"screen_name": "SenatorShaheen"},"id": 906146863199305729}
{"user":{"screen_name": "SenatorShaheen"},"id": 893171411824541696}
{"user":{"screen_name": "SenatorShaheen"},"id": 893112086561214464}
{"user":{"screen_name": "SenatorShaheen"},"id": 893111675460702208}
{"user":{"screen_name": "SenatorShaheen"},"id": 880951933531455489}
{"user":{"screen_name": "SenatorShaheen"},"id": 880433274228748289}
{"user":{"screen_name": "SenatorShaheen"},"id": 875751078192721920}
{"user":{"screen_name": "SenatorShaheen"},"id": 874976227894976512}
{"user":{"screen_name": "SenatorShaheen"},"id": 874668341532794882}
{"user":{"screen_name": "SenatorShaheen"},"id": 865245162229903360}
{"user":{"screen_name": "SenatorShaheen"},"id": 862095206476386304}
{"user":{"screen_name": "SenatorShaheen"},"id": 860240890778054657}
{"user":{"screen_name": "SenatorShaheen"},"id": 860203326931128320}
{"user":{"screen_name": "SenatorShaheen"},"id": 859487068057214976}
{"user":{"screen_name": "SenatorShaheen"},"id": 850035475465351170}
{"user":{"screen_name": "SenatorShaheen"},"id": 849315797256331266}
{"user":{"screen_name": "SenatorShaheen"},"id": 846812112240480257}
{"user":{"screen_name": "SenatorShaheen"},"id": 845023568597602304}
{"user":{"screen_name": "SenatorShaheen"},"id": 842046814320766976}
{"user":{"screen_name": "SenatorShaheen"},"id": 837147290842333184}
{"user":{"screen_name": "SenatorShaheen"},"id": 830813316498989060}
{"user":{"screen_name": "SenatorShaheen"},"id": 828442194826641413}
{"user":{"screen_name": "SenatorShaheen"},"id": 827200934077927424}
{"user":{"screen_name": "SenatorShaheen"},"id": 825403417967329287}
{"user":{"screen_name": "SenatorShaheen"},"id": 825159357788803072}
{"user":{"screen_name": "SenatorShaheen"},"id": 823669831216074752}
{"user":{"screen_name": "SenatorShaheen"},"id": 823581271788027904}
{"user":{"screen_name": "SenatorShaheen"},"id": 817124581668483072}
{"user":{"screen_name": "SenatorShaheen"},"id": 809439260189331456}
{"user":{"screen_name": "SenatorShaheen"},"id": 809439161606348800}
{"user":{"screen_name": "SenatorShaheen"},"id": 809106256304676864}
{"user":{"screen_name": "SenatorShaheen"},"id": 809103659690786817}
{"user":{"screen_name": "SenatorShaheen"},"id": 804370505478377474}
{"user":{"screen_name": "SenatorShaheen"},"id": 725373080793657344}
{"user":{"screen_name": "SenatorShaheen"},"id": 667464368884424704}
{"user":{"screen_name": "SenatorShaheen"},"id": 658711647037575168}
{"user":{"screen_name": "SenatorShaheen"},"id": 639442117077680128}
{"user":{"screen_name": "SenatorShaheen"},"id": 611364888359890944}
{"user":{"screen_name": "SenatorShaheen"},"id": 588359932799541248}
{"user":{"screen_name": "SenatorShaheen"},"id": 562085202869362690}
{"user":{"screen_name": "SenatorShaheen"},"id": 562029087532015617}
{"user":{"screen_name": "SenatorShaheen"},"id": 557010768940789760}
{"user":{"screen_name": "SenatorShaheen"},"id": 554081730769207297}
{"user":{"screen_name": "SenatorShaheen"},"id": 554022848873123840}
{"user":{"screen_name": "SenatorShaheen"},"id": 507261604590022656}
