{"user":{"screen_name": "SenBlumenthal"},"id": 838534614444564481}
{"user":{"screen_name": "SenBlumenthal"},"id": 838524104693145601}
{"user":{"screen_name": "SenBlumenthal"},"id": 838520528562450432}
{"user":{"screen_name": "SenBlumenthal"},"id": 837365783940448256}
{"user":{"screen_name": "SenBlumenthal"},"id": 837335325923999744}
{"user":{"screen_name": "SenBlumenthal"},"id": 836788819252883456}
{"user":{"screen_name": "SenBlumenthal"},"id": 831959887609528331}
{"user":{"screen_name": "SenBlumenthal"},"id": 831524200401739776}
{"user":{"screen_name": "SenBlumenthal"},"id": 830220249723191296}
{"user":{"screen_name": "SenBlumenthal"},"id": 829864684878716933}
{"user":{"screen_name": "SenBlumenthal"},"id": 829864515374370816}
{"user":{"screen_name": "SenBlumenthal"},"id": 829780910165876736}
{"user":{"screen_name": "SenBlumenthal"},"id": 829380414422781952}
{"user":{"screen_name": "SenBlumenthal"},"id": 829112047522693121}
{"user":{"screen_name": "SenBlumenthal"},"id": 828769675140071425}
{"user":{"screen_name": "SenBlumenthal"},"id": 828644251584045056}
{"user":{"screen_name": "SenBlumenthal"},"id": 826806866772635649}
{"user":{"screen_name": "SenBlumenthal"},"id": 826806552459931649}
{"user":{"screen_name": "SenBlumenthal"},"id": 826239959564681216}
{"user":{"screen_name": "SenBlumenthal"},"id": 826239778513420289}
{"user":{"screen_name": "SenBlumenthal"},"id": 825391055143043073}
{"user":{"screen_name": "SenBlumenthal"},"id": 818962168003653632}
{"user":{"screen_name": "SenBlumenthal"},"id": 818838721143312384}
{"user":{"screen_name": "SenBlumenthal"},"id": 818480447776837633}
{"user":{"screen_name": "SenBlumenthal"},"id": 816676698183897088}
{"user":{"screen_name": "SenBlumenthal"},"id": 806911517731876864}
{"user":{"screen_name": "SenBlumenthal"},"id": 800898309930045440}
{"user":{"screen_name": "SenBlumenthal"},"id": 750762490347347968}
{"user":{"screen_name": "SenBlumenthal"},"id": 742046518887251968}
{"user":{"screen_name": "SenBlumenthal"},"id": 672162371750744064}
