{"user":{"screen_name": "senrobportman"},"id": 890741971945443328}
{"user":{"screen_name": "senrobportman"},"id": 890718397092306945}
{"user":{"screen_name": "senrobportman"},"id": 890711959548592128}
{"user":{"screen_name": "senrobportman"},"id": 890708158078963712}
{"user":{"screen_name": "senrobportman"},"id": 890693554351218688}
{"user":{"screen_name": "senrobportman"},"id": 890692527250001920}
{"user":{"screen_name": "senrobportman"},"id": 890677171974361088}
{"user":{"screen_name": "senrobportman"},"id": 890671136425607168}
{"user":{"screen_name": "senrobportman"},"id": 890667491046735872}
{"user":{"screen_name": "senrobportman"},"id": 890665751455117313}
{"user":{"screen_name": "senrobportman"},"id": 890650787231039488}
{"user":{"screen_name": "senrobportman"},"id": 890644790370586624}
{"user":{"screen_name": "senrobportman"},"id": 890617041572450305}
{"user":{"screen_name": "senrobportman"},"id": 890571512234860545}
{"user":{"screen_name": "senrobportman"},"id": 890382678033387520}
{"user":{"screen_name": "senrobportman"},"id": 890317909234470914}
{"user":{"screen_name": "senrobportman"},"id": 890316335976153088}
{"user":{"screen_name": "senrobportman"},"id": 890314924601331713}
{"user":{"screen_name": "senrobportman"},"id": 890293309922562050}
{"user":{"screen_name": "senrobportman"},"id": 890272059716235265}
{"user":{"screen_name": "senrobportman"},"id": 890270036803375104}
{"user":{"screen_name": "senrobportman"},"id": 890218641861619713}
{"user":{"screen_name": "senrobportman"},"id": 890217538289840129}
{"user":{"screen_name": "senrobportman"},"id": 890207126018297861}
{"user":{"screen_name": "senrobportman"},"id": 890205442894426114}
{"user":{"screen_name": "senrobportman"},"id": 889979272500314112}
{"user":{"screen_name": "senrobportman"},"id": 889978345324253184}
{"user":{"screen_name": "senrobportman"},"id": 889934321007702017}
{"user":{"screen_name": "senrobportman"},"id": 889933880446382081}
{"user":{"screen_name": "senrobportman"},"id": 889932697925189633}
{"user":{"screen_name": "senrobportman"},"id": 889931777439145984}
{"user":{"screen_name": "senrobportman"},"id": 889929838248828929}
{"user":{"screen_name": "senrobportman"},"id": 889897515407077376}
{"user":{"screen_name": "senrobportman"},"id": 889897269205626881}
{"user":{"screen_name": "senrobportman"},"id": 889859287325036544}
{"user":{"screen_name": "senrobportman"},"id": 889850729309102082}
{"user":{"screen_name": "senrobportman"},"id": 889832607696867328}
{"user":{"screen_name": "senrobportman"},"id": 889830551301091329}
{"user":{"screen_name": "senrobportman"},"id": 889594252010901505}
{"user":{"screen_name": "senrobportman"},"id": 889580045798342661}
{"user":{"screen_name": "senrobportman"},"id": 889559923104854016}
{"user":{"screen_name": "senrobportman"},"id": 889180309723521024}
{"user":{"screen_name": "senrobportman"},"id": 889176034368770050}
{"user":{"screen_name": "senrobportman"},"id": 889172018939035648}
{"user":{"screen_name": "senrobportman"},"id": 889168236008411138}
{"user":{"screen_name": "senrobportman"},"id": 888880332073689089}
{"user":{"screen_name": "senrobportman"},"id": 888877330516525057}
{"user":{"screen_name": "senrobportman"},"id": 888792122769514496}
{"user":{"screen_name": "senrobportman"},"id": 888579338853126144}
{"user":{"screen_name": "senrobportman"},"id": 888166017788203009}
{"user":{"screen_name": "senrobportman"},"id": 888157070545039360}
{"user":{"screen_name": "senrobportman"},"id": 888135166195113984}
{"user":{"screen_name": "senrobportman"},"id": 887780961152364545}
{"user":{"screen_name": "senrobportman"},"id": 887740574383714308}
{"user":{"screen_name": "senrobportman"},"id": 887736545934942208}
{"user":{"screen_name": "senrobportman"},"id": 887714405126942721}
{"user":{"screen_name": "senrobportman"},"id": 887709287757340672}
{"user":{"screen_name": "senrobportman"},"id": 887429773370298368}
{"user":{"screen_name": "senrobportman"},"id": 887428781320916993}
{"user":{"screen_name": "senrobportman"},"id": 887427935573073920}
{"user":{"screen_name": "senrobportman"},"id": 887427474828734466}
{"user":{"screen_name": "senrobportman"},"id": 887395228038180864}
{"user":{"screen_name": "senrobportman"},"id": 887335555314462720}
{"user":{"screen_name": "senrobportman"},"id": 887108549435904001}
{"user":{"screen_name": "senrobportman"},"id": 886678076272377856}
{"user":{"screen_name": "senrobportman"},"id": 886625224375943168}
{"user":{"screen_name": "senrobportman"},"id": 886321219913502720}
{"user":{"screen_name": "senrobportman"},"id": 886275168783355904}
{"user":{"screen_name": "senrobportman"},"id": 886248996712394752}
{"user":{"screen_name": "senrobportman"},"id": 886245470607089665}
{"user":{"screen_name": "senrobportman"},"id": 886242199725236224}
{"user":{"screen_name": "senrobportman"},"id": 886240190074941440}
{"user":{"screen_name": "senrobportman"},"id": 885957578789924864}
{"user":{"screen_name": "senrobportman"},"id": 885918864164388864}
{"user":{"screen_name": "senrobportman"},"id": 885918447858831361}
{"user":{"screen_name": "senrobportman"},"id": 885638218875416576}
{"user":{"screen_name": "senrobportman"},"id": 885586632585482242}
{"user":{"screen_name": "senrobportman"},"id": 885585123676213248}
{"user":{"screen_name": "senrobportman"},"id": 885583609335226369}
{"user":{"screen_name": "senrobportman"},"id": 885581866253918209}
{"user":{"screen_name": "senrobportman"},"id": 833376631402094593}
{"user":{"screen_name": "senrobportman"},"id": 833349932358758401}
{"user":{"screen_name": "senrobportman"},"id": 833073870957481984}
{"user":{"screen_name": "senrobportman"},"id": 833039253315665921}
{"user":{"screen_name": "senrobportman"},"id": 832670074565713920}
{"user":{"screen_name": "senrobportman"},"id": 832631951903166464}
{"user":{"screen_name": "senrobportman"},"id": 831910282649858048}
{"user":{"screen_name": "senrobportman"},"id": 831668097446719488}
{"user":{"screen_name": "senrobportman"},"id": 831579717534883844}
{"user":{"screen_name": "senrobportman"},"id": 831307471251718145}
{"user":{"screen_name": "senrobportman"},"id": 831238772461236224}
{"user":{"screen_name": "senrobportman"},"id": 830920471013122053}
{"user":{"screen_name": "senrobportman"},"id": 830823548897800192}
{"user":{"screen_name": "senrobportman"},"id": 830817494440964098}
{"user":{"screen_name": "senrobportman"},"id": 829756305267183617}
{"user":{"screen_name": "senrobportman"},"id": 829501349951844352}
{"user":{"screen_name": "senrobportman"},"id": 829394878849236996}
{"user":{"screen_name": "senrobportman"},"id": 829388145263276033}
{"user":{"screen_name": "senrobportman"},"id": 829089591579856897}
{"user":{"screen_name": "senrobportman"},"id": 829087371664773120}
{"user":{"screen_name": "senrobportman"},"id": 829078422659936257}
{"user":{"screen_name": "senrobportman"},"id": 829063932304310273}
{"user":{"screen_name": "senrobportman"},"id": 829036259783897088}
{"user":{"screen_name": "senrobportman"},"id": 829032482871922690}
{"user":{"screen_name": "senrobportman"},"id": 829027199923675136}
{"user":{"screen_name": "senrobportman"},"id": 829024546573410304}
{"user":{"screen_name": "senrobportman"},"id": 828992334977175552}
{"user":{"screen_name": "senrobportman"},"id": 828809062959685633}
{"user":{"screen_name": "senrobportman"},"id": 828806419457703937}
{"user":{"screen_name": "senrobportman"},"id": 828749112455491584}
{"user":{"screen_name": "senrobportman"},"id": 828743520563388416}
{"user":{"screen_name": "senrobportman"},"id": 828741156053872640}
{"user":{"screen_name": "senrobportman"},"id": 828737703034384385}
{"user":{"screen_name": "senrobportman"},"id": 828690075932295169}
{"user":{"screen_name": "senrobportman"},"id": 828350490962440192}
{"user":{"screen_name": "senrobportman"},"id": 828339926085300224}
{"user":{"screen_name": "senrobportman"},"id": 828320816311918592}
{"user":{"screen_name": "senrobportman"},"id": 828310499141914624}
{"user":{"screen_name": "senrobportman"},"id": 828294123136352256}
{"user":{"screen_name": "senrobportman"},"id": 828286817061392384}
{"user":{"screen_name": "senrobportman"},"id": 827992125690109952}
{"user":{"screen_name": "senrobportman"},"id": 827966962978455552}
{"user":{"screen_name": "senrobportman"},"id": 827958909172322304}
{"user":{"screen_name": "senrobportman"},"id": 827944563721568256}
{"user":{"screen_name": "senrobportman"},"id": 827936006582120450}
{"user":{"screen_name": "senrobportman"},"id": 827930976680542210}
{"user":{"screen_name": "senrobportman"},"id": 827646530509225984}
{"user":{"screen_name": "senrobportman"},"id": 827608519209779200}
{"user":{"screen_name": "senrobportman"},"id": 827309067295158273}
{"user":{"screen_name": "senrobportman"},"id": 827300324436221952}
{"user":{"screen_name": "senrobportman"},"id": 827293525855322113}
{"user":{"screen_name": "senrobportman"},"id": 827285409172332544}
{"user":{"screen_name": "senrobportman"},"id": 827279906295803905}
{"user":{"screen_name": "senrobportman"},"id": 827184577424801794}
{"user":{"screen_name": "senrobportman"},"id": 827162409420746753}
{"user":{"screen_name": "senrobportman"},"id": 826898930654969857}
{"user":{"screen_name": "senrobportman"},"id": 826805360786812928}
{"user":{"screen_name": "senrobportman"},"id": 826607504306077697}
{"user":{"screen_name": "senrobportman"},"id": 826605742396469248}
{"user":{"screen_name": "senrobportman"},"id": 826603592274546688}
{"user":{"screen_name": "senrobportman"},"id": 826471103618953220}
{"user":{"screen_name": "senrobportman"},"id": 826105196254081024}
{"user":{"screen_name": "senrobportman"},"id": 825794238436737026}
{"user":{"screen_name": "senrobportman"},"id": 825764203554230272}
{"user":{"screen_name": "senrobportman"},"id": 825744432494415873}
{"user":{"screen_name": "senrobportman"},"id": 825742017015771136}
{"user":{"screen_name": "senrobportman"},"id": 825741972950417409}
{"user":{"screen_name": "senrobportman"},"id": 825706400198324224}
{"user":{"screen_name": "senrobportman"},"id": 825486731172577280}
{"user":{"screen_name": "senrobportman"},"id": 825468244244848640}
{"user":{"screen_name": "senrobportman"},"id": 825442075302907904}
{"user":{"screen_name": "senrobportman"},"id": 825414948222357507}
{"user":{"screen_name": "senrobportman"},"id": 825052760366252032}
{"user":{"screen_name": "senrobportman"},"id": 825051247237435392}
{"user":{"screen_name": "senrobportman"},"id": 825018893680795648}
{"user":{"screen_name": "senrobportman"},"id": 824778724503588864}
{"user":{"screen_name": "senrobportman"},"id": 824004500805603328}
{"user":{"screen_name": "senrobportman"},"id": 823942460850245632}
{"user":{"screen_name": "senrobportman"},"id": 823653892906975235}
{"user":{"screen_name": "senrobportman"},"id": 823652010167828480}
{"user":{"screen_name": "senrobportman"},"id": 823570417860444160}
{"user":{"screen_name": "senrobportman"},"id": 822206250595196928}
{"user":{"screen_name": "senrobportman"},"id": 820355556061810688}
{"user":{"screen_name": "senrobportman"},"id": 820354548774486016}
{"user":{"screen_name": "senrobportman"},"id": 820009620047613952}
{"user":{"screen_name": "senrobportman"},"id": 819959949618913281}
{"user":{"screen_name": "senrobportman"},"id": 819956677407453184}
{"user":{"screen_name": "senrobportman"},"id": 819945049953812484}
{"user":{"screen_name": "senrobportman"},"id": 819564344027422721}
{"user":{"screen_name": "senrobportman"},"id": 819563336597520385}
{"user":{"screen_name": "senrobportman"},"id": 819562142034755586}
{"user":{"screen_name": "senrobportman"},"id": 819399904254685184}
{"user":{"screen_name": "senrobportman"},"id": 817468927890587650}
{"user":{"screen_name": "senrobportman"},"id": 815974281440063488}
{"user":{"screen_name": "senrobportman"},"id": 805471660459618304}
