{"user":{"screen_name": "maziehirono"},"id": 919000905630052357}
{"user":{"screen_name": "maziehirono"},"id": 907385354474450944}
{"user":{"screen_name": "maziehirono"},"id": 904518194328678404}
{"user":{"screen_name": "maziehirono"},"id": 898607057397575680}
{"user":{"screen_name": "maziehirono"},"id": 890818953496338432}
{"user":{"screen_name": "maziehirono"},"id": 890706403983282176}
{"user":{"screen_name": "maziehirono"},"id": 887768481512476672}
{"user":{"screen_name": "maziehirono"},"id": 879473706883526656}
{"user":{"screen_name": "maziehirono"},"id": 879062823845978116}
{"user":{"screen_name": "maziehirono"},"id": 862777269219192836}
{"user":{"screen_name": "maziehirono"},"id": 861974843775963137}
{"user":{"screen_name": "maziehirono"},"id": 826172396902170624}
{"user":{"screen_name": "maziehirono"},"id": 799375690604957696}
{"user":{"screen_name": "maziehirono"},"id": 626146032712347649}
