{"user":{"screen_name": "SenJohnMcCain"},"id": 920770513416474625}
{"user":{"screen_name": "SenJohnMcCain"},"id": 918085781322977280}
{"user":{"screen_name": "SenJohnMcCain"},"id": 917837943380828160}
{"user":{"screen_name": "SenJohnMcCain"},"id": 907633006118043649}
{"user":{"screen_name": "SenJohnMcCain"},"id": 907597930894327808}
{"user":{"screen_name": "SenJohnMcCain"},"id": 907596012671393793}
{"user":{"screen_name": "SenJohnMcCain"},"id": 907372853108113409}
{"user":{"screen_name": "SenJohnMcCain"},"id": 907371708499333124}
{"user":{"screen_name": "SenJohnMcCain"},"id": 907360914516664321}
{"user":{"screen_name": "SenJohnMcCain"},"id": 907348643413413889}
{"user":{"screen_name": "SenJohnMcCain"},"id": 907331786988015616}
{"user":{"screen_name": "SenJohnMcCain"},"id": 907309209234046977}
{"user":{"screen_name": "SenJohnMcCain"},"id": 907308226445807623}
{"user":{"screen_name": "SenJohnMcCain"},"id": 907302633018466307}
{"user":{"screen_name": "SenJohnMcCain"},"id": 905851834169950213}
{"user":{"screen_name": "SenJohnMcCain"},"id": 905849698484936704}
{"user":{"screen_name": "SenJohnMcCain"},"id": 903970019037650945}
{"user":{"screen_name": "SenJohnMcCain"},"id": 903668344594804736}
{"user":{"screen_name": "SenJohnMcCain"},"id": 902684226100670464}
{"user":{"screen_name": "SenJohnMcCain"},"id": 902682172464627713}
{"user":{"screen_name": "SenJohnMcCain"},"id": 902681306751832064}
{"user":{"screen_name": "SenJohnMcCain"},"id": 900880562398920704}
{"user":{"screen_name": "SenJohnMcCain"},"id": 900805394951540736}
{"user":{"screen_name": "SenJohnMcCain"},"id": 899303911110176768}
{"user":{"screen_name": "SenJohnMcCain"},"id": 898988966246064128}
{"user":{"screen_name": "SenJohnMcCain"},"id": 898988574976212992}
{"user":{"screen_name": "SenJohnMcCain"},"id": 898969341907140608}
{"user":{"screen_name": "SenJohnMcCain"},"id": 896010442123902976}
{"user":{"screen_name": "SenJohnMcCain"},"id": 891783805442433024}
{"user":{"screen_name": "SenJohnMcCain"},"id": 888514935013158912}
{"user":{"screen_name": "SenJohnMcCain"},"id": 887354453740990465}
{"user":{"screen_name": "SenJohnMcCain"},"id": 883047107866898432}
{"user":{"screen_name": "SenJohnMcCain"},"id": 882290994112217089}
{"user":{"screen_name": "SenJohnMcCain"},"id": 882249570708738048}
{"user":{"screen_name": "SenJohnMcCain"},"id": 882248634930044928}
{"user":{"screen_name": "SenJohnMcCain"},"id": 881929540196487172}
{"user":{"screen_name": "SenJohnMcCain"},"id": 881923770524594176}
{"user":{"screen_name": "SenJohnMcCain"},"id": 881922399356112897}
{"user":{"screen_name": "SenJohnMcCain"},"id": 880452088609820672}
{"user":{"screen_name": "SenJohnMcCain"},"id": 875076117534736385}
{"user":{"screen_name": "SenJohnMcCain"},"id": 870291962380910592}
{"user":{"screen_name": "SenJohnMcCain"},"id": 851816068771393537}
{"user":{"screen_name": "SenJohnMcCain"},"id": 850019158515482624}
{"user":{"screen_name": "SenJohnMcCain"},"id": 849660353847939072}
{"user":{"screen_name": "SenJohnMcCain"},"id": 846464868647620608}
{"user":{"screen_name": "SenJohnMcCain"},"id": 842035297252712449}
{"user":{"screen_name": "SenJohnMcCain"},"id": 839240981480357888}
{"user":{"screen_name": "SenJohnMcCain"},"id": 828983971274948609}
{"user":{"screen_name": "SenJohnMcCain"},"id": 827567573579493381}
{"user":{"screen_name": "SenJohnMcCain"},"id": 827195992541949953}
{"user":{"screen_name": "SenJohnMcCain"},"id": 825774037720772608}
{"user":{"screen_name": "SenJohnMcCain"},"id": 825773834750005248}
{"user":{"screen_name": "SenJohnMcCain"},"id": 825773307249176580}
{"user":{"screen_name": "SenJohnMcCain"},"id": 825772969867747328}
{"user":{"screen_name": "SenJohnMcCain"},"id": 821491093590208517}
