{"user":{"screen_name": "SenatorIsakson"},"id": 921073037264457728}
{"user":{"screen_name": "SenatorIsakson"},"id": 918230241738477568}
{"user":{"screen_name": "SenatorIsakson"},"id": 914807210831699968}
{"user":{"screen_name": "SenatorIsakson"},"id": 913475268211339264}
{"user":{"screen_name": "SenatorIsakson"},"id": 913130245208793088}
{"user":{"screen_name": "SenatorIsakson"},"id": 910197246301523969}
{"user":{"screen_name": "SenatorIsakson"},"id": 905204925239619585}
{"user":{"screen_name": "SenatorIsakson"},"id": 897888546299793408}
{"user":{"screen_name": "SenatorIsakson"},"id": 896441010645061634}
{"user":{"screen_name": "SenatorIsakson"},"id": 894660808436846592}
{"user":{"screen_name": "SenatorIsakson"},"id": 892409575110053888}
{"user":{"screen_name": "SenatorIsakson"},"id": 889929634619502593}
{"user":{"screen_name": "SenatorIsakson"},"id": 884921387483365376}
{"user":{"screen_name": "SenatorIsakson"},"id": 872888207838515202}
{"user":{"screen_name": "SenatorIsakson"},"id": 872438005151272963}
{"user":{"screen_name": "SenatorIsakson"},"id": 871782681696243712}
{"user":{"screen_name": "SenatorIsakson"},"id": 867367383421378562}
{"user":{"screen_name": "SenatorIsakson"},"id": 867108130957787137}
{"user":{"screen_name": "SenatorIsakson"},"id": 860553387754086400}
{"user":{"screen_name": "SenatorIsakson"},"id": 860116125853638656}
{"user":{"screen_name": "SenatorIsakson"},"id": 857969541393108996}
{"user":{"screen_name": "SenatorIsakson"},"id": 850385040638869505}
{"user":{"screen_name": "SenatorIsakson"},"id": 850186228989399040}
{"user":{"screen_name": "SenatorIsakson"},"id": 850009959064637440}
{"user":{"screen_name": "SenatorIsakson"},"id": 849261753968013312}
{"user":{"screen_name": "SenatorIsakson"},"id": 846821263490387970}
{"user":{"screen_name": "SenatorIsakson"},"id": 846401426582622208}
{"user":{"screen_name": "SenatorIsakson"},"id": 844667092284649473}
{"user":{"screen_name": "SenatorIsakson"},"id": 842447282607915008}
{"user":{"screen_name": "SenatorIsakson"},"id": 838831835593510914}
{"user":{"screen_name": "SenatorIsakson"},"id": 836791033300193281}
{"user":{"screen_name": "SenatorIsakson"},"id": 836776784037359617}
{"user":{"screen_name": "SenatorIsakson"},"id": 836386410189975552}
{"user":{"screen_name": "SenatorIsakson"},"id": 834847689284153348}
{"user":{"screen_name": "SenatorIsakson"},"id": 834441136366301184}
{"user":{"screen_name": "SenatorIsakson"},"id": 834407817545129984}
{"user":{"screen_name": "SenatorIsakson"},"id": 834095454119923713}
{"user":{"screen_name": "SenatorIsakson"},"id": 833713631657336834}
{"user":{"screen_name": "SenatorIsakson"},"id": 832696234800340993}
{"user":{"screen_name": "SenatorIsakson"},"id": 831963472774758400}
{"user":{"screen_name": "SenatorIsakson"},"id": 831313555425263616}
{"user":{"screen_name": "SenatorIsakson"},"id": 830170698136031232}
{"user":{"screen_name": "SenatorIsakson"},"id": 830055686344232960}
{"user":{"screen_name": "SenatorIsakson"},"id": 829835577021308928}
{"user":{"screen_name": "SenatorIsakson"},"id": 829487346320101378}
{"user":{"screen_name": "SenatorIsakson"},"id": 829012549005934594}
{"user":{"screen_name": "SenatorIsakson"},"id": 828761086497288192}
{"user":{"screen_name": "SenatorIsakson"},"id": 828682755693219841}
{"user":{"screen_name": "SenatorIsakson"},"id": 827613245972287489}
{"user":{"screen_name": "SenatorIsakson"},"id": 827551545331953669}
{"user":{"screen_name": "SenatorIsakson"},"id": 826512609285398528}
{"user":{"screen_name": "SenatorIsakson"},"id": 826222858481315840}
{"user":{"screen_name": "SenatorIsakson"},"id": 825088920970989569}
{"user":{"screen_name": "SenatorIsakson"},"id": 823979773764530176}
{"user":{"screen_name": "SenatorIsakson"},"id": 819559589586862080}
{"user":{"screen_name": "SenatorIsakson"},"id": 742113873386307584}
