{"user":{"screen_name": "TheEllenShow"},"id": 990989705121480704}
{"user":{"screen_name": "TheEllenShow"},"id": 990734601340370944}
{"user":{"screen_name": "TheEllenShow"},"id": 990006086462726144}
{"user":{"screen_name": "TheEllenShow"},"id": 989980674919563264}
{"user":{"screen_name": "TheEllenShow"},"id": 989970069282209792}
{"user":{"screen_name": "TheEllenShow"},"id": 989956002421161984}
{"user":{"screen_name": "TheEllenShow"},"id": 989943050821488640}
{"user":{"screen_name": "TheEllenShow"},"id": 989935137621082112}
{"user":{"screen_name": "TheEllenShow"},"id": 989927361750614016}
{"user":{"screen_name": "TheEllenShow"},"id": 989913446010372097}
{"user":{"screen_name": "TheEllenShow"},"id": 989633489338167297}
{"user":{"screen_name": "TheEllenShow"},"id": 989621282172948481}
{"user":{"screen_name": "TheEllenShow"},"id": 989602507662938112}
{"user":{"screen_name": "TheEllenShow"},"id": 989598066779996160}
{"user":{"screen_name": "TheEllenShow"},"id": 989583400875900928}
{"user":{"screen_name": "TheEllenShow"},"id": 989571404180815872}
{"user":{"screen_name": "TheEllenShow"},"id": 989556423376883712}
{"user":{"screen_name": "TheEllenShow"},"id": 989538432874512384}
{"user":{"screen_name": "TheEllenShow"},"id": 989256405839368192}
{"user":{"screen_name": "TheEllenShow"},"id": 989238473633611776}
{"user":{"screen_name": "TheEllenShow"},"id": 989230874410414080}
{"user":{"screen_name": "TheEllenShow"},"id": 989221015187156993}
{"user":{"screen_name": "TheEllenShow"},"id": 989205149963829253}
{"user":{"screen_name": "TheEllenShow"},"id": 989192672408563712}
{"user":{"screen_name": "TheEllenShow"},"id": 988898042358022145}
{"user":{"screen_name": "TheEllenShow"},"id": 988875843966386176}
{"user":{"screen_name": "TheEllenShow"},"id": 988860298651099137}
{"user":{"screen_name": "TheEllenShow"},"id": 988852850439540737}
{"user":{"screen_name": "TheEllenShow"},"id": 988831835017826305}
{"user":{"screen_name": "TheEllenShow"},"id": 988541879431057408}
{"user":{"screen_name": "TheEllenShow"},"id": 988523036511907840}
{"user":{"screen_name": "TheEllenShow"},"id": 988517146962477056}
{"user":{"screen_name": "TheEllenShow"},"id": 988493601893167106}
{"user":{"screen_name": "TheEllenShow"},"id": 988471221615448064}
{"user":{"screen_name": "TheEllenShow"},"id": 988458651852550145}
{"user":{"screen_name": "TheEllenShow"},"id": 988433502386323456}
{"user":{"screen_name": "TheEllenShow"},"id": 988250593704607744}
{"user":{"screen_name": "TheEllenShow"},"id": 988205167462907904}
{"user":{"screen_name": "TheEllenShow"},"id": 988144692951896064}
{"user":{"screen_name": "TheEllenShow"},"id": 988133088436805632}
{"user":{"screen_name": "TheEllenShow"},"id": 988102457724092416}
{"user":{"screen_name": "TheEllenShow"},"id": 987874675807014912}
{"user":{"screen_name": "TheEllenShow"},"id": 987819920548220928}
{"user":{"screen_name": "TheEllenShow"},"id": 987807567295336448}
{"user":{"screen_name": "TheEllenShow"},"id": 987519516027441153}
{"user":{"screen_name": "TheEllenShow"},"id": 987463490754392064}
{"user":{"screen_name": "TheEllenShow"},"id": 987450875151990785}
{"user":{"screen_name": "TheEllenShow"},"id": 987442632581304320}
{"user":{"screen_name": "TheEllenShow"},"id": 987428896013352960}
{"user":{"screen_name": "TheEllenShow"},"id": 987412813801930753}
{"user":{"screen_name": "TheEllenShow"},"id": 987403462454333440}
{"user":{"screen_name": "TheEllenShow"},"id": 987394414044524544}
{"user":{"screen_name": "TheEllenShow"},"id": 987375933794349056}
{"user":{"screen_name": "TheEllenShow"},"id": 987148328684077056}
{"user":{"screen_name": "TheEllenShow"},"id": 987139078578569216}
